{
  "kind": "coverage_report",
  "version": "1.0",
  "generatedAt": "2026-02-07T13:02:04.644Z",
  "sources": {
    "buildRequest": true,
    "implementationPlan": true
  },
  "requirements": {
    "total": 1,
    "implemented": 1,
    "items": [
      {
        "id": "REQ-15",
        "summary": "Update the Image Memory section so each image card (both front image side and back message side) renders in a fixed 2:3 aspect ratio (width:height), replacing the current 4:3 aspect ratio sizing.",
        "status": "implemented",
        "plannedFiles": [
          "frontend/src/components/memories/ImageMemoryCard.tsx",
          "frontend/src/index.css"
        ],
        "matchedFiles": [
          "frontend/src/components/memories/ImageMemoryCard.tsx"
        ]
      }
    ]
  },
  "changedFiles": [
    "build-request.json",
    "feature_evidence.json",
    "frontend-file-summaries.txt",
    "frontend-implementation-plan.json",
    "frontend/src/components/memories/ImageMemoryCard.tsx",
    "project_state.json",
    "scratch/component-selection.json",
    "spec.md",
    "spec_vs_diff_report.json"
  ]
}